exponential_degradation/__init__.py
exponential_degradation/model.py
exponential_degradation/py.typed
exponential_degradation_model-0.1.0.dist-info/METADATA
exponential_degradation_model-0.1.0.dist-info/WHEEL
exponential_degradation_model-0.1.0.dist-info/licenses/LICENSE
exponential_degradation_model-0.1.0.dist-info/RECORD
