Metadata-Version: 2.4
Name: exponential-degradation-model
Version: 0.1.0
Summary: A Python implementation of the exponential degradation model for remaining useful life (RUL) prediction
Project-URL: Homepage, https://github.com/houtj/exponentialDegradationModel
Project-URL: Repository, https://github.com/houtj/exponentialDegradationModel
Project-URL: Issues, https://github.com/houtj/exponentialDegradationModel/issues
Project-URL: Documentation, https://github.com/houtj/exponentialDegradationModel#readme
Author-email: Tianjun HOU <houtj@example.com>
Maintainer-email: Tianjun HOU <houtj@example.com>
License: MIT License
License-File: LICENSE
Keywords: RUL,degradation-modeling,exponential-degradation,predictive-maintenance,prognostics,reliability,remaining-useful-life
Classifier: Development Status :: 3 - Alpha
Classifier: Intended Audience :: Developers
Classifier: Intended Audience :: Science/Research
Classifier: License :: OSI Approved :: MIT License
Classifier: Operating System :: OS Independent
Classifier: Programming Language :: Python :: 3
Classifier: Programming Language :: Python :: 3.8
Classifier: Programming Language :: Python :: 3.9
Classifier: Programming Language :: Python :: 3.10
Classifier: Programming Language :: Python :: 3.11
Classifier: Programming Language :: Python :: 3.12
Classifier: Programming Language :: Python :: 3.13
Classifier: Topic :: Scientific/Engineering
Classifier: Topic :: Scientific/Engineering :: Information Analysis
Classifier: Topic :: Software Development :: Libraries :: Python Modules
Requires-Python: >=3.8
Requires-Dist: build>=1.2.2.post1
Requires-Dist: numpy>=1.20.0
Requires-Dist: scipy>=1.7.0
Requires-Dist: twine>=6.1.0
Provides-Extra: dev
Requires-Dist: jupyter>=1.0.0; extra == 'dev'
Requires-Dist: matplotlib>=3.5.0; extra == 'dev'
Requires-Dist: notebook>=6.5.0; extra == 'dev'
